rwproperty.py
rwproperty.txt
setup.py
rwproperty.egg-info/PKG-INFO
rwproperty.egg-info/SOURCES.txt
rwproperty.egg-info/dependency_links.txt
rwproperty.egg-info/top_level.txt
