Metadata-Version: 1.0
Name: rwproperty
Version: 1.0
Summary: Read & write properties
Home-page: http://www.z3lab.org/sections/blogs/philipp-weitershausen/2006_05_29_pycon-06-lightning-talk
Author: Philipp von Weitershausen
Author-email: grok-dev@zope.org
License: ZPL
Download-URL: http://codespeak.net/svn/user/philikon/rwproperty#egg=rwproperty-dev
Platform: UNKNOWN
